[{"first_name": "Jackie", "last_name": "Calderon", "email": "lesliesimon@example.org"}, {"first_name": "Lauren", "last_name": "Arnold", "email": "christopher84@example.net"}, {"first_name": "Frank", "last_name": "Tran", "email": "hesschristopher@example.net"}, {"first_name": "Donna", "last_name": "Holland", "email": "iwelch@example.net"}, {"first_name": "Autumn", "last_name": "Chavez", "email": "hlawrence@example.org"}, {"first_name": "Alex", "last_name": "Russo", "email": "andersondonna@example.org"}, {"first_name": "Susan", "last_name": "Washington", "email": "tara43@example.net"}, {"first_name": "Heather", "last_name": "Bruce", "email": "xcarpenter@example.com"}, {"first_name": "Brandy", "last_name": "Jacobs", "email": "peter86@example.com"}, {"first_name": "Christina", "last_name": "James", "email": "jyoung@example.net"}, {"first_name": "Justin", "last_name": "Wilson", "email": "crosbylaura@example.net"}, {"first_name": "Paul", "last_name": "Martin", "email": "ewingrebecca@example.net"}, {"first_name": "Jackie", "last_name": "Webb", "email": "atkinsonscott@example.org"}, {"first_name": "Tonya", "last_name": "Schmidt", "email": "olsentara@example.com"}, {"first_name": "Hannah", "last_name": "Banks", "email": "tphillips@example.net"}, {"first_name": "Michael", "last_name": "Vaughn", "email": "dalexander@example.com"}, {"first_name": "Melissa", "last_name": "Swanson", "email": "alison42@example.org"}, {"first_name": "Gregory", "last_name": "Espinoza", "email": "davisdean@example.net"}, {"first_name": "Vickie", "last_name": "Stewart", "email": "smithbrandy@example.com"}, {"first_name": "Tricia", "last_name": "Cochran", "email": "sharpmichelle@example.net"}, {"first_name": "Tiffany", "last_name": "Harris", "email": "thomas66@example.net"}, {"first_name": "Kyle", "last_name": "Perkins", "email": "whitney06@example.net"}, {"first_name": "Matthew", "last_name": "Scott", "email": "diazjulia@example.org"}, {"first_name": "Michael", "last_name": "Cook", "email": "thomas55@example.org"}, {"first_name": "Zachary", "last_name": "Morales", "email": "erik63@example.net"}, {"first_name": "David", "last_name": "Tucker", "email": "carol61@example.com"}, {"first_name": "Amy", "last_name": "Sanders", "email": "qmoody@example.com"}, {"first_name": "Rebecca", "last_name": "Mann", "email": "ccervantes@example.org"}, {"first_name": "Courtney", "last_name": "Campbell", "email": "mary29@example.org"}, {"first_name": "Leah", "last_name": "Fleming", "email": "escott@example.net"}, {"first_name": "Desiree", "last_name": "Meyer", "email": "rwilkins@example.net"}, {"first_name": "Seth", "last_name": "Brown", "email": "laceygallagher@example.org"}, {"first_name": "Stephen", "last_name": "James", "email": "davidmartinez@example.net"}, {"first_name": "Rhonda", "last_name": "Patterson", "email": "uortiz@example.org"}, {"first_name": "Heidi", "last_name": "Marsh", "email": "jessicaclark@example.com"}, {"first_name": "Michael", "last_name": "Martin", "email": "patriciapatterson@example.net"}, {"first_name": "Cory", "last_name": "Sanchez", "email": "louis33@example.com"}, {"first_name": "Ashley", "last_name": "Blair", "email": "christinaperez@example.net"}, {"first_name": "Janet", "last_name": "Hall", "email": "teresa00@example.net"}, {"first_name": "Lauren", "last_name": "Gardner", "email": "ymcdowell@example.org"}, {"first_name": "Vanessa", "last_name": "Bryant", "email": "laura24@example.net"}, {"first_name": "Katherine", "last_name": "Baker", "email": "jessica84@example.net"}, {"first_name": "Elizabeth", "last_name": "Jones", "email": "bethanyscott@example.org"}, {"first_name": "Nathan", "last_name": "Snyder", "email": "fhayes@example.org"}, {"first_name": "Elizabeth", "last_name": "Turner", "email": "brownsydney@example.net"}, {"first_name": "Jessica", "last_name": "Salazar", "email": "hchoi@example.com"}, {"first_name": "Yolanda", "last_name": "Martin", "email": "stephenallen@example.com"}, {"first_name": "Marcus", "last_name": "Walker", "email": "laurenperry@example.org"}, {"first_name": "Michael", "last_name": "Foster", "email": "kaitlyngray@example.com"}, {"first_name": "Penny", "last_name": "Wang", "email": "tbrooks@example.net"}, {"first_name": "Monica", "last_name": "Wilson", "email": "jessica56@example.org"}, {"first_name": "Summer", "last_name": "Proctor", "email": "taylorgarner@example.com"}, {"first_name": "Nicole", "last_name": "Harrington", "email": "knightveronica@example.com"}, {"first_name": "Ashley", "last_name": "Roman", "email": "glynch@example.net"}, {"first_name": "Brittany", "last_name": "Richmond", "email": "colemichele@example.net"}, {"first_name": "Jason", "last_name": "Payne", "email": "lestershannon@example.net"}, {"first_name": "Yvonne", "last_name": "Miller", "email": "diazkristin@example.net"}, {"first_name": "Michael", "last_name": "Sampson", "email": "usmith@example.com"}, {"first_name": "Joanna", "last_name": "Bean", "email": "johnsoncaleb@example.org"}, {"first_name": "Ashley", "last_name": "Willis", "email": "michaelmiddleton@example.org"}, {"first_name": "Brandon", "last_name": "Barrera", "email": "uherrera@example.org"}, {"first_name": "Rachel", "last_name": "Barnes", "email": "camposrobert@example.org"}, {"first_name": "Tony", "last_name": "Garcia", "email": "logan18@example.org"}, {"first_name": "John", "last_name": "Jensen", "email": "amanda90@example.org"}, {"first_name": "Jesus", "last_name": "Fernandez", "email": "seanwhite@example.com"}, {"first_name": "Sharon", "last_name": "Proctor", "email": "perezryan@example.org"}, {"first_name": "Travis", "last_name": "Garcia", "email": "ulang@example.org"}, {"first_name": "Julie", "last_name": "Gonzalez", "email": "ronaldbailey@example.net"}, {"first_name": "Angela", "last_name": "Oliver", "email": "chadroberts@example.net"}, {"first_name": "Seth", "last_name": "Nunez", "email": "daniellejohnson@example.net"}, {"first_name": "Shane", "last_name": "Cook", "email": "jonjames@example.org"}, {"first_name": "John", "last_name": "Morgan", "email": "pcollins@example.org"}, {"first_name": "Tracy", "last_name": "Jackson", "email": "caleb29@example.org"}, {"first_name": "Albert", "last_name": "Ferguson", "email": "gregg41@example.net"}, {"first_name": "Maureen", "last_name": "Walsh", "email": "richard94@example.org"}, {"first_name": "Victoria", "last_name": "Hernandez", "email": "cstout@example.net"}, {"first_name": "Ryan", "last_name": "Durham", "email": "jburton@example.com"}, {"first_name": "Martin", "last_name": "Bryan", "email": "yvonnediaz@example.org"}, {"first_name": "Debra", "last_name": "Flowers", "email": "laura33@example.net"}, {"first_name": "Melinda", "last_name": "Graham", "email": "caitlin84@example.com"}, {"first_name": "Joseph", "last_name": "Martin", "email": "christensenblake@example.org"}, {"first_name": "Angela", "last_name": "Morales", "email": "angelaflores@example.net"}, {"first_name": "Christopher", "last_name": "Patterson", "email": "johnsonheather@example.net"}, {"first_name": "Frances", "last_name": "Davis", "email": "urosales@example.net"}, {"first_name": "Rebekah", "last_name": "Bradford", "email": "zmartinez@example.net"}, {"first_name": "Ashley", "last_name": "Maddox", "email": "psolis@example.net"}, {"first_name": "Daniel", "last_name": "Young", "email": "ksmith@example.org"}, {"first_name": "Sarah", "last_name": "Neal", "email": "rachelolson@example.net"}, {"first_name": "Joseph", "last_name": "Ferguson", "email": "cartertroy@example.net"}, {"first_name": "Steven", "last_name": "Holloway", "email": "asmith@example.com"}, {"first_name": "Donald", "last_name": "Mills", "email": "martinjoshua@example.com"}, {"first_name": "Christopher", "last_name": "Thompson", "email": "jason20@example.net"}, {"first_name": "Ashley", "last_name": "Powers", "email": "scottsara@example.net"}, {"first_name": "Erika", "last_name": "Pittman", "email": "jason40@example.org"}, {"first_name": "Nancy", "last_name": "Arnold", "email": "richardlee@example.org"}, {"first_name": "Warren", "last_name": "Flores", "email": "garymiles@example.org"}, {"first_name": "Melissa", "last_name": "Lopez", "email": "timothy05@example.net"}, {"first_name": "Kelsey", "last_name": "Gordon", "email": "lauracooper@example.net"}, {"first_name": "Bailey", "last_name": "Thompson", "email": "patricksmith@example.net"}, {"first_name": "Larry", "last_name": "Lee", "email": "davidmitchell@example.org"}]